CHANGELOG.txt
LICENSE.txt
MANIFEST.in
README.rst
requirements.txt
setup.py
appspace/__init__.py
appspace/builders.py
appspace/keys.py
appspace/managers.py
appspace/registry.py
appspace/spaces.py
appspace/utils.py
appspace.egg-info/PKG-INFO
appspace.egg-info/SOURCES.txt
appspace.egg-info/dependency_links.txt
appspace.egg-info/not-zip-safe
appspace.egg-info/requires.txt
appspace.egg-info/top_level.txt
appspace/tests/__init__.py
appspace/tests/apps.py
appspace/tests/test_core.py